[
    {
        "id": 1, 
        "name": "Maceta Luz",
        "description": "Pintada a mano, en tonos violetas, verdes, amarillos y con un colibri",
        "price": 5220,
        "stock": 5,
        "category": "Pintadas"
    },
    {
        "id": 2, 
        "name": "Maceta Sol",
        "description": "Pintada a mano, en tonos violetas, verdes, amarillos y con un colibri",
        "price": 5220,
        "stock": 8,
        "category": "Pintadas"
    },
    {
        "id": 3, 
        "name": "Maceta Tierra",
        "description": "Pintada a mano y barnizada, con doble barniz para una mayor durabilidad, en tonos violetas, verdes, amarillos y con un colibri",
        "price": 7220,
        "stock": 9,
        "category": "Barnizadas"
    },
    {
        "id": 4, 
        "name": "Maceta Fuego",
        "description": "Pintada a mano y barnizada, con doble barniz para una mayor durabilidad, en tonos violetas, verdes, amarillos y con un colibri",
        "price": 7220,
        "stock": 18,
        "category": "Barnizadas"
    },
    {
        "id": 5, 
        "name": "Maceta Paz",
        "description": "Pintada a mano, en tonos violetas, verdes, amarillos y con un colibri",
        "price": 5220,
        "stock": 4,
        "category": "Pintadas"
    },
    {
        "id": 6, 
        "name": "Maceta Star",
        "description": "Pintada a mano y barnizada, con doble barniz para una mayor durabilidad, en tonos violetas, verdes, amarillos y con un colibri",
        "price": 7220,
        "stock": 7,
        "category": "Barnizadas"
    }
]